adafruit_ds18x20.py
adafruit_circuitpython_ds18x20-1.4.7.dist-info/licenses/LICENSE
adafruit_circuitpython_ds18x20-1.4.7.dist-info/METADATA
adafruit_circuitpython_ds18x20-1.4.7.dist-info/WHEEL
adafruit_circuitpython_ds18x20-1.4.7.dist-info/top_level.txt
adafruit_circuitpython_ds18x20-1.4.7.dist-info/RECORD
