Metadata-Version: 2.4
Name: adafruit-circuitpython-ds18x20
Version: 1.4.7
Summary: CircuitPython driver for Dallas 1-Wire temperature sensor.
Author-email: Adafruit Industries <circuitpython@adafruit.com>
License: MIT
Project-URL: Homepage, https://github.com/adafruit/Adafruit_CircuitPython_DS18X20
Keywords: adafruit,1-wire,temperature,sensor,ds18x20,hardware,breakout,micropython,circuitpython
Classifier: Intended Audience :: Developers
Classifier: Topic :: Software Development :: Libraries
Classifier: Topic :: Software Development :: Embedded Systems
Classifier: Topic :: System :: Hardware
Classifier: License :: OSI Approved :: MIT License
Classifier: Programming Language :: Python :: 3
License-File: LICENSE
Requires-Dist: Adafruit-Blinka
Requires-Dist: adafruit-circuitpython-onewire
Requires-Dist: typing-extensions~=4.0
Provides-Extra: optional
Dynamic: license-file
